Metadata-Version: 2.1
Name: salesforce
Version: 0.0.1
Summary: A package to perform API calls to Salesforce
Home-page: https://gitlab.com/wjwatkinson/salesforce
Author: Will Watkinson
Author-email: wjwats4295@gmail.com
License: UNKNOWN
Platform: UNKNOWN
Classifier: Programming Language :: Python :: 3
Classifier: License :: OSI Approved :: MIT License
Classifier: Operating System :: OS Independent
Requires-Python: >=3.6
